Metadata-Version: 1.2
Name: latte-fama
Version: 0.0.1
Summary: Automated report tooling
Home-page: https://github.com/milesgranger/latte-fama
Author: Diana Spencer, Miles Granger
Maintainer: Miles Granger, Diana Spencer
License: UNKNOWN
Keywords: report bi business intelligence
Platform: UNKNOWN
Classifier: Development Status :: 3 - Alpha
Classifier: Intended Audience :: Developers
Classifier: Intended Audience :: Financial and Insurance Industry
Classifier: Intended Audience :: Information Technology
Classifier: Intended Audience :: Science/Research
Classifier: Programming Language :: Python
Classifier: Programming Language :: Python :: 3.6
Classifier: Programming Language :: Python :: 3.5
Classifier: Programming Language :: Python :: 3 :: Only
Classifier: Operating System :: Microsoft :: Windows
Classifier: Operating System :: POSIX
Classifier: Operating System :: Unix
Classifier: Operating System :: MacOS :: MacOS X
